algorig/__init__.py
algorig/app.py
algorig/cli.py
algorig/config.py
algorig-0.2.dist-info/METADATA
algorig-0.2.dist-info/WHEEL
algorig-0.2.dist-info/entry_points.txt
algorig-0.2.dist-info/top_level.txt
algorig-0.2.dist-info/RECORD
