Metadata-Version: 2.1
Name: algorig
Version: 0.2
Summary: algorand development rig
Home-page: https://github.com/kadirpekel/algorig
Author: Kadir Pekel
Author-email: kadirpekel@gmail.com
Requires-Python: >=3.10
Requires-Dist: py-algorand-sdk (>=2.0.0)
Requires-Dist: pyteal (==0.21.0)
Requires-Dist: komandr (>=2.0.1)
Requires-Dist: gdparser (>=0.0.2)
Provides-Extra: dev
Requires-Dist: pytest ; extra == 'dev'
Requires-Dist: flake8 ; extra == 'dev'
